apricopt_synthesis/__init__.py
apricopt_synthesis/cli.py
apricopt_synthesis/input.py
apricopt_synthesis/run.py
apricopt_synthesis/therapy_synthesis.py
apricopt_synthesis/blackbox/SynthesisBlackBox.py
apricopt_synthesis/blackbox/SynthesisModel.py
apricopt_synthesis/blackbox/SynthesisProcess.py
apricopt_synthesis/blackbox/TreatmentModel.py
apricopt_synthesis/blackbox/__init__.py
apricopt_synthesis/blackbox/sbml/DigitalTwinNotSetError.py
apricopt_synthesis/blackbox/sbml/SBMLSynthesisBlackBox.py
apricopt_synthesis/blackbox/sbml/__init__.py
apricopt_synthesis-0.0.1a1.dev1.dist-info/COPYING
apricopt_synthesis-0.0.1a1.dev1.dist-info/METADATA
apricopt_synthesis-0.0.1a1.dev1.dist-info/WHEEL
apricopt_synthesis-0.0.1a1.dev1.dist-info/top_level.txt
apricopt_synthesis-0.0.1a1.dev1.dist-info/RECORD
