Metadata-Version: 2.1
Name: apricopt-synthesis
Version: 0.0.1a1.dev1
Summary: A python library
Home-page: http://mclab.di.uniroma1.it
Author: Marco Esposito
Author-email: esposito@di.uniroma1.it
License: UNKNOWN
Platform: UNKNOWN
Classifier: Programming Language :: Python :: 3
Classifier: License :: OSI Approved :: GNU General Public License v3 (GPLv3)
Classifier: Operating System :: OS Independent
Requires-Python: >=3.6
Requires-Dist: Pillow (==8.0.1)
Requires-Dist: PyYAML (==5.3.1)
Requires-Dist: apricopt (==0.0.2a1dev3)
Requires-Dist: attrs (==20.3.0)
Requires-Dist: chaospy (==4.2.1)
Requires-Dist: codetiming (==1.2.0)
Requires-Dist: colorama (==0.4.4)
Requires-Dist: cycler (==0.10.0)
Requires-Dist: importlib-metadata (==3.1.0)
Requires-Dist: jsonschema (==3.2.0)
Requires-Dist: kiwisolver (==1.3.1)
Requires-Dist: matplotlib (==3.3.3)
Requires-Dist: mpmath (==1.1.0)
Requires-Dist: numpoly (==1.1.0)
Requires-Dist: numpy (==1.19.4)
Requires-Dist: pandas (==1.1.4)
Requires-Dist: petab (==0.1.12)
Requires-Dist: pyparsing (==2.4.7)
Requires-Dist: pyrsistent (==0.17.3)
Requires-Dist: python-copasi (==4.29.227)
Requires-Dist: python-dateutil (==2.8.1)
Requires-Dist: python-libsbml (==5.18.3)
Requires-Dist: pytz (==2020.4)
Requires-Dist: scipy (==1.5.4)
Requires-Dist: seaborn (==0.11.0)
Requires-Dist: six (==1.15.0)
Requires-Dist: sympy (==1.6.2)
Requires-Dist: zipp (==3.4.0)
